{
	"format_version": "1.8.0",
	"animations": {
		"jump": {
			"animation_length": 0.375,
			"bones": {
				"torso": {
					"rotation": {
						"0.0": [-273.99793, 9.58615, 275.34811],
						"0.0833": [-447.03099, 12.95354, 448.51224],
						"0.1667": [-406.05733, 14.92308, 407.94774],
						"0.3333": [-273.99793, 9.58615, 275.34811]
					},
					"position": {
						"0.0": [0, -2, 0],
						"0.0833": [0, 4, 0],
						"0.1667": [0, 5, 0],
						"0.3333": [0, -2, 0]
					}
				},
				"mouth": {
					"rotation": {
						"0.0": [0, 0, 0],
						"0.0833": [0, 0, -20],
						"0.1667": [0, 0, -10.83],
						"0.3333": [0, 0, 0]
					}
				},
				"rightfront": {
					"rotation": {
						"0.0": [-22.5, 0, 0],
						"0.125": [7.5, 0, 0],
						"0.1667": [20, 0, 0],
						"0.3333": [-22.5, 0, 0]
					},
					"position": {
						"0.0": [0, -1, 0],
						"0.0833": [0, 5, 0],
						"0.1667": [0, 6, 0],
						"0.3333": [0, -1, 0]
					}
				},
				"2fr": {
					"rotation": {
						"0.0": [22.5, 0, 0],
						"0.125": [-22.5, 0, 0],
						"0.3333": [22.5, 0, 0]
					}
				},
				"3fr": {
					"rotation": {
						"0.0": [0, 0, 0],
						"0.125": [85, 0, 0]
					}
				},
				"leftfront": {
					"rotation": {
						"0.0": [-20, 0, 0],
						"0.0833": [25, 0, 0],
						"0.1667": [30, 0, 0],
						"0.3333": [-20, 0, 0]
					},
					"position": {
						"0.0": [0, -1, 0],
						"0.0833": [0, 5, 0],
						"0.1667": [0, 6, 0],
						"0.3333": [0, -1, 0]
					}
				},
				"2fl": {
					"rotation": {
						"0.0": [22.5, 0, 0],
						"0.0833": [-50, 0, 0],
						"0.3333": [22.5, 0, 0]
					}
				},
				"3fl": {
					"rotation": {
						"0.0": [0, 0, 0],
						"0.0833": [95, 0, 0],
						"0.3333": [0, 0, 0]
					}
				},
				"leftback": {
					"rotation": {
						"0.0": [-20, 0, 0],
						"0.125": [47.5, 0, 0],
						"0.1667": [55, 0, 0],
						"0.3333": [-20, 0, 0]
					},
					"position": {
						"0.0": [0, -1, 0],
						"0.0833": [0, 3, 0],
						"0.1667": [0, 4, 0],
						"0.3333": [0, -1, 0]
					}
				},
				"2lb": {
					"rotation": {
						"0.0": [22.5, 0, 0],
						"0.125": [-57.5, 0, 0],
						"0.3333": [22.5, 0, 0]
					}
				},
				"3lb": {
					"rotation": {
						"0.0": [0, 0, 0],
						"0.125": [90, 0, 0],
						"0.3333": [0, 0, 0]
					}
				},
				"rightback": {
					"rotation": {
						"0.0": [-22.5, 0, 0],
						"0.125": [50, 0, 0],
						"0.1667": [52.5, 0, 0],
						"0.3333": [-22.5, 0, 0]
					},
					"position": {
						"0.0": [0, -1, 0],
						"0.0833": [0, 4, 0],
						"0.125": [0, 3, 0],
						"0.1667": [0, 5, 0],
						"0.3333": [0, -1, 0]
					}
				},
				"2rb": {
					"rotation": {
						"0.0": [22.5, 0, 0],
						"0.125": [-64.98435, 2.38422, 0.7522],
						"0.3333": [22.5, 0, 0]
					}
				},
				"3rb": {
					"rotation": {
						"0.0": [0, 0, 0],
						"0.125": [107.5, 0, 0]
					}
				}
			}
		},
		"idle": {
			"loop": "hold_on_last_frame",
			"animation_length": 39.66667,
			"bones": {
				"torso": {
					"rotation": {
						"0.0": [0, 0, 0],
						"0.4583": [90, 25, -90],
						"1.2083": [0, 0, 0],
						"10.4167": [0, 0, 0],
						"10.75": [0, 0, -2],
						"10.9583": [0, 0, 1.43],
						"11.7083": [0, 0, 0],
						"12.0417": [175.99939, 3.99939, -181.00061],
						"12.4167": [178.54859, 14.36526, -187.52611],
						"12.4583": [177.50491, 14.36352, -187.68746],
						"13.4583": [177.4565, 14.32166, -191.55965],
						"14.5417": [-7.51678, 11.09407, 10.13926],
						"15.125": [0, 0, 0],
						"22.9167": [0, 0, 0],
						"22.9583": [-2.5, 0, 0],
						"23.0": [-5, 0, 0],
						"23.0833": [-7.5, 0, 0],
						"23.2917": [-5, 0, 0],
						"23.4583": [-7.5, 0, 0],
						"23.5417": [-2.5, 0, 0],
						"23.625": [0, 0, 0],
						"23.6667": [2.5, 0, 0],
						"23.7083": [0, 0, 0],
						"30.7083": [0, 0, 0],
						"31.0417": [0, 0, -2],
						"31.25": [0, 0, 1.43],
						"32.0": [0, 0, 0],
						"32.3333": [175.99939, 3.99939, -181.00061],
						"32.7083": [178.54859, 14.36526, -187.52611],
						"32.75": [177.50491, 14.36352, -187.68746],
						"33.75": [177.4565, 14.32166, -191.55965],
						"34.8333": [-7.51678, 11.09407, 10.13926],
						"35.4167": [0, 0, 0],
						"37.0833": [90, 25, -90],
						"37.4167": [0, -7.5, 0],
						"37.5417": [-78, 12, 78.5]
					},
					"position": {
						"0.0": [0, 0, 0.5],
						"0.4583": [0, 0, 1.5],
						"1.2083": [0, -2, 0],
						"1.2917": [0, -2.1, 0],
						"11.7083": [0, -2.1, 0],
						"15.125": [0, -2, 0],
						"15.2083": [0, -2.1, 0],
						"32.0": [0, -2.1, 0],
						"35.4167": [0, -2, 0],
						"35.5": [0, -2.1, 0],
						"37.0833": [0, 0, 1.5],
						"37.4167": [0, 0, 0.5]
					}
				},
				"mouth": {
					"rotation": {
						"0.0": [0, 0, -7.5],
						"0.4583": [0, 0, 0],
						"10.625": [0, 0, -2.5],
						"10.8333": [0, 0, -5],
						"10.875": [0, 0, 0],
						"11.0417": [0, 0, -2.5],
						"11.4167": [0, 0, 2.5],
						"11.4583": [0, 0, 0],
						"11.9583": [0, 0, -2.5],
						"12.375": [0, 0, -5],
						"12.75": [0, 0, -2.5],
						"13.625": [0, 0, 0],
						"13.875": [0, 0, -2.5],
						"14.1667": [0, 0, -5],
						"14.375": [0, 0, -2.5],
						"14.7083": [0, 0, 0],
						"16.125": [0, 0, -1],
						"22.7083": [0, 0, -3.5],
						"22.9167": [0, 0, 1.5],
						"23.0417": [0, 0, -1],
						"23.25": [0, 0, -3.5],
						"23.4583": [0, 0, 1.5],
						"23.6667": [0, 0, -1],
						"23.7917": [0, 0, 1.5],
						"30.9167": [0, 0, -2.5],
						"31.125": [0, 0, -5],
						"31.1667": [0, 0, 0],
						"31.3333": [0, 0, -2.5],
						"31.7083": [0, 0, 2.5],
						"31.75": [0, 0, 0],
						"32.25": [0, 0, -2.5],
						"32.6667": [0, 0, -5],
						"33.0417": [0, 0, -2.5],
						"33.9167": [0, 0, 0],
						"34.1667": [0, 0, -2.5],
						"34.4583": [0, 0, -5],
						"34.6667": [0, 0, -2.5],
						"35.0": [0, 0, 0],
						"36.4167": [0, 0, -1],
						"37.0833": [0, 0, 0],
						"37.4167": [0, 0, -7.5],
						"37.5417": [0, 0, -2.5],
						"38.375": [0, 0, -5],
						"38.75": [0, 0, -10],
						"39.0833": [0, 0, -5],
						"39.375": [0, 0, 2.5],
						"39.5": [0, 0, -2.5]
					}
				},
				"rightfront": {
					"rotation": {
						"0.0": [0, 0, 0.01],
						"0.4583": [0, 0, 0.01],
						"1.2083": [-30, 0, 0],
						"11.7083": [-30, 0, 0],
						"12.25": [-30, 9.5, 0],
						"13.4583": [-30, 9.5, 0],
						"14.5417": [-30, 24.5, 0],
						"15.125": [-30, 0, 0],
						"22.9583": [-30, 0, 0],
						"23.625": [-30, 0, 0],
						"32.0": [-30, 0, 0],
						"32.5417": [-30, 9.5, 0],
						"33.75": [-30, 9.5, 0],
						"34.8333": [-30, 24.5, 0],
						"35.4167": [-30, 0, 0],
						"37.0833": [0, 0, 0.01],
						"37.4167": [0, 0, 0.01],
						"37.5417": [1, 0, 0]
					},
					"position": {
						"0.0": [0, 0, 0],
						"0.4583": [0, -1, 0],
						"1.2083": [0, -2, -1],
						"11.7083": [0, -2, -1],
						"12.25": [0.8, -2, -1],
						"13.4583": [0.8, -2, -1],
						"14.5417": [-0.5, -2, -0.4],
						"15.125": [0, -2, -1],
						"22.9583": [0, -2, -1],
						"23.625": [0, -2, -1],
						"32.0": [0, -2, -1],
						"32.5417": [0.8, -2, -1],
						"33.75": [0.8, -2, -1],
						"34.8333": [-0.5, -2, -0.4],
						"35.4167": [0, -2, -1],
						"37.0833": [0, -1, 0],
						"37.4167": [0, 0, 0]
					}
				},
				"eye1": {
					"rotation": {
						"14.8333": [0, 0, 0],
						"22.7083": [0, 0, 0],
						"35.125": [0, 0, 0]
					},
					"position": {
						"0.0": [0, 0, 0],
						"1.7917": [0, 0, 0],
						"1.9583": [0.1, -1.7, 0],
						"11.7083": [0.1, -1.7, 0],
						"11.875": [0.1, -1.5, 0],
						"12.0417": [0.1, -1.7, 0],
						"13.5": [0.1, -1.7, 0],
						"13.7083": [0.1, -1, 0],
						"13.9167": [0.1, -0.1, 0],
						"13.9583": [0.1, 0.2, 0],
						"14.8333": [0.1, 0.2, 0],
						"15.0833": [0.1, -0.8, 0],
						"15.2917": [0.1, -1.4, 0],
						"15.375": [0.1, -1.6, 0],
						"22.7083": [0.1, -1.6, 0],
						"22.9167": [0.1, -1.1, 0],
						"23.0833": [0.1, -0.7, 0],
						"23.2917": [0.1, -0.8, 0],
						"23.4167": [0.1, -1.2, 0],
						"23.5417": [0.1, -1.7, 0],
						"32.0": [0.1, -1.7, 0],
						"32.1667": [0.1, -1.5, 0],
						"32.3333": [0.1, -1.7, 0],
						"33.7917": [0.1, -1.7, 0],
						"34.0": [0.1, -1, 0],
						"34.2083": [0.1, -0.1, 0],
						"34.25": [0.1, 0.2, 0],
						"35.125": [0.1, 0.2, 0],
						"35.375": [0.1, -0.8, 0],
						"35.5833": [0.1, -1.4, 0],
						"35.6667": [0.1, -1.6, 0],
						"36.25": [0.1, -1.7, 0],
						"36.375": [0, 0, 0],
						"37.4167": [0, 0, 0]
					},
					"scale": {
						"1.7917": [1, 1, 1],
						"1.9583": [1, 2.1, 1.1],
						"11.7083": [1, 2.1, 1.1],
						"13.7083": [1, 2.1, 1.1],
						"32.0": [1, 2.1, 1.1],
						"34.0": [1, 2.1, 1.1],
						"36.25": [1, 2.1, 1.1],
						"36.375": [1, 1, 1]
					}
				},
				"leftfront": {
					"rotation": {
						"0.0": [0, 0, 0.01],
						"0.4583": [0, 0, 0.01],
						"1.2083": [-30, 0, 0],
						"11.7083": [-30, 0, 0],
						"12.25": [-30, -37.5, 0],
						"13.4583": [-30, -37.5, 0],
						"14.5417": [-30, -20, 0],
						"15.125": [-30, 0, 0],
						"22.9583": [-30, 0, 0],
						"23.2083": [-30, 0, -4],
						"23.25": [-30, 0, -10],
						"23.4167": [-30, 0, -14],
						"23.4583": [-43.26496, -4.51741, -18.47445],
						"23.625": [-30, 0, 0],
						"23.6667": [-30, 0, 1],
						"23.7083": [-32, 0, -1],
						"32.0": [-30, 0, 0],
						"32.5417": [-30, -37.5, 0],
						"33.75": [-30, -37.5, 0],
						"34.8333": [-30, -20, 0],
						"35.4167": [-30, 0, 0],
						"37.0833": [0, 0, 0.01],
						"37.4167": [0, 0, 0.01],
						"37.5417": [2, 0, 0]
					},
					"position": {
						"0.0": [0, 0, 0],
						"0.4583": [0, -1, 0],
						"1.2083": [0, -2, -1],
						"11.7083": [0, -2, -1],
						"12.25": [0.6, -2, -0.8],
						"13.4583": [0.6, -2, -0.8],
						"14.5417": [-0.7, -2, -0.8],
						"15.125": [0, -2, -1],
						"22.9583": [0, -2, -1],
						"23.0833": [0, -1.2, -1],
						"23.2083": [0, -0.5, -1],
						"23.25": [0.4, -1.5, -1],
						"23.375": [0.5, -1.5, -1],
						"23.4167": [0.8, -1.7, -1],
						"23.4583": [0.5, -1.5, -1],
						"23.625": [0, -2, -1],
						"32.0": [0, -2, -1],
						"32.5417": [0.6, -2, -0.8],
						"33.75": [0.6, -2, -0.8],
						"34.8333": [-0.7, -2, -0.8],
						"35.4167": [0, -2, -1],
						"37.0833": [0, -1, 0],
						"37.4167": [0, 0, 0]
					}
				},
				"leftback": {
					"rotation": {
						"0.0": [0, 0, 0],
						"0.4583": [52.5, 0, 0],
						"1.125": [-30, 0, 0],
						"11.7083": [-30, 0, 0],
						"15.0417": [-30, 0, 0],
						"22.9583": [-30, 0, 0],
						"23.625": [-30, 0, 0],
						"32.0": [-30, 0, 0],
						"35.3333": [-22.5, 0, 0],
						"37.0833": [40, 0, 0],
						"37.4167": [0, 0, 0]
					},
					"position": {
						"0.0": [0, 0, 0],
						"0.4583": [0, 2.1, -0.5],
						"1.2083": [0, -2, -1],
						"11.7083": [0, -2, -1],
						"15.125": [0, -2, -1],
						"22.9583": [0, -2, -1],
						"23.625": [0, -2, -1],
						"32.0": [0, -2, -1],
						"35.4167": [0, -2, -1],
						"37.0833": [0, 2.1, -0.5],
						"37.4167": [0, 0, 0]
					}
				},
				"rightback": {
					"rotation": {
						"0.0": [0, 0, 0],
						"0.4583": [52.5, 0, 0],
						"1.125": [-30, 0, 0],
						"11.7083": [-30, 0, 0],
						"15.0417": [-30, 0, 0],
						"22.9583": [-30, 0, 0],
						"23.625": [-30, 0, 0],
						"32.0": [-30, 0, 0],
						"35.125": [-30, 0, 0],
						"35.3333": [-30, 0, 0],
						"37.0833": [45, 0, 0],
						"37.4167": [0, 0, 0]
					},
					"position": {
						"0.0": [0, 0, 0],
						"0.4583": [0, 2.1, -0.5],
						"1.2083": [0, -2, -1],
						"11.7083": [0, -2, -1],
						"15.125": [0, -2, -1],
						"22.9583": [0, -2, -1],
						"23.625": [0, -2, -1],
						"32.0": [0, -2, -1],
						"35.4167": [0, -2, -1],
						"37.0833": [0, 2.1, -0.5],
						"37.4167": [0, 0, 0]
					}
				},
				"2fr": {
					"rotation": {
						"0.0": [0, 0, 0],
						"0.4583": [23, 0, 0],
						"1.2083": [48.5, 0, 0],
						"15.125": [48.5, 0, 0],
						"22.9583": [48.5, 0, 0],
						"23.2083": [48.5, 0, 0],
						"23.625": [48.5, 0, 0],
						"35.4167": [48.5, 0, 0],
						"37.0833": [23, 0, 0],
						"37.4167": [0, 0, 0]
					},
					"position": {
						"0.0": [0, 0, 0],
						"22.9583": [0, 0, 0],
						"23.2083": [0, 0, 0],
						"23.625": [0, 0, 0],
						"37.4167": [0, 0, 0]
					}
				},
				"3fr": {
					"rotation": {
						"0.0": [0, 0, 0],
						"0.4583": [-23, 0, 0],
						"1.2083": [-19, 0, 0],
						"22.9583": [-19, 0, 0],
						"23.2083": [-19, 0, 0],
						"23.625": [-19, 0, 0],
						"37.0833": [-23, 0, 0],
						"37.4167": [0, 0, 0]
					},
					"position": {
						"0.0": [0, 0, 0],
						"22.9583": [0, 0, 0],
						"23.2083": [0, 0, 0],
						"23.625": [0, 0, 0],
						"37.4167": [0, 0, 0]
					}
				},
				"2fl": {
					"rotation": {
						"0.0": [0, 0, 0],
						"0.4583": [23, 0, 0],
						"1.2083": [48.5, 0, 0],
						"22.9583": [48.5, 0, 0],
						"23.2083": [51, 0, 0],
						"23.25": [48.5, 0, 0],
						"23.375": [-1.5, 0, 0],
						"23.4167": [-39, 0, 0],
						"23.4583": [8, 0, 0],
						"23.625": [48.5, 0, 0],
						"37.0833": [23, 0, 0],
						"37.4167": [0, 0, 0]
					},
					"position": {
						"0.0": [0, 0, 0],
						"22.9583": [0, 0, 0],
						"23.2083": [0, 0, 0],
						"23.625": [0, 0, 0],
						"37.4167": [0, 0, 0]
					}
				},
				"3fl": {
					"rotation": {
						"0.0": [0, 0, 0],
						"0.4583": [-23, 0, 0],
						"1.2083": [-19, 0, 0],
						"22.9583": [-19, 0, 0],
						"23.2083": [-26.5, 0, 0],
						"23.25": [73, 0, 0],
						"23.375": [28.5, 0, 0],
						"23.4583": [48.5, 0, 0],
						"23.625": [-19, 0, 0],
						"37.0833": [-23, 0, 0],
						"37.4167": [0, 0, 0]
					},
					"position": {
						"0.0": [0, 0, 0],
						"22.9583": [0, 0, 0],
						"23.2083": [0, 0, 0],
						"23.625": [0, 0, 0],
						"37.4167": [0, 0, 0]
					}
				},
				"2lb": {
					"rotation": {
						"0.0": [0, 0, 0],
						"0.4583": [-67.93659, 0, 0],
						"1.125": [48.5, 0, 0],
						"35.3333": [38.11, 0, 0],
						"37.0833": [-67.73, 0, 0],
						"37.5417": [5.5, 0, 0]
					},
					"position": {
						"0.0": [0, 0, 0],
						"0.4583": [0, -0.42063, -0.05538]
					}
				},
				"3lb": {
					"rotation": {
						"0.0": [0, 0, 0],
						"0.4583": [35, 0, 0],
						"1.125": [-19, 0, 0],
						"22.9583": [-19, 0, 0],
						"23.2083": [-19, 0, 0],
						"23.625": [-19, 0, 0],
						"35.3333": [-7.02, 0, 0],
						"37.0833": [35, 0, 0],
						"37.4167": [0, 0, 0]
					},
					"position": {
						"0.0": [0, 0, 0],
						"22.9583": [0, 0, 0],
						"23.2083": [0, 0, 0],
						"23.625": [0, 0, 0],
						"37.4167": [0, 0, 0]
					}
				},
				"2rb": {
					"rotation": {
						"0.0": [0, 0, 0],
						"0.4583": [-67.9366, 0, 0],
						"1.125": [48.5, -0.4206, -0.0554],
						"35.125": [48.5, -0.4206, -0.0554],
						"37.0833": [-75.40842, -0.4206, -0.0554],
						"37.5417": [1.5, -0.4206, -0.0554]
					},
					"position": {
						"0.0": [0, 0, 0],
						"0.4583": [0, -0.4206, -0.0554]
					}
				},
				"3rb": {
					"rotation": {
						"0.0": [0, 0, 0],
						"0.4583": [35, 0, 0],
						"1.125": [-19, 0, 0],
						"22.9583": [-19, 0, 0],
						"23.2083": [-19, 0, 0],
						"23.625": [-19, 0, 0],
						"35.125": [-19, 0, 0],
						"37.0833": [37.5, 0, 0],
						"37.4167": [0, 0, 0]
					},
					"position": {
						"0.0": [0, 0, 0],
						"22.9583": [0, 0, 0],
						"23.2083": [0, 0, 0],
						"23.625": [0, 0, 0],
						"37.4167": [0, 0, 0]
					}
				},
				"eye2": {
					"position": {
						"1.7917": [0, 0, 0],
						"1.9583": [0.1, -1.7, 0],
						"11.7083": [0.1, -1.7, 0],
						"11.9167": [0.1, -0.7, 0],
						"12.0417": [0.1, 0.3, 0],
						"12.0833": [0.1, 0.15, 0],
						"12.125": [0.1, 0.2, 0],
						"13.5": [0.1, 0.2, 0],
						"13.7083": [0.1, -1, 0],
						"13.9167": [0.1, -1.7, 0],
						"22.7083": [0.1, -1.7, 0],
						"22.9167": [0.1, -0.7, 0],
						"23.0833": [0.1, -0.8, 0],
						"23.2917": [0.1, -0.7, 0],
						"23.4167": [0.1, -1.2, 0],
						"23.5417": [0.1, -1.7, 0],
						"23.6667": [0.1, -1.6, 0],
						"23.7083": [0.1, -1.7, 0],
						"32.0": [0.1, -1.7, 0],
						"32.2083": [0.1, -0.7, 0],
						"32.3333": [0.1, 0.3, 0],
						"32.375": [0.1, 0.15, 0],
						"32.4167": [0.1, 0.2, 0],
						"33.7917": [0.1, 0.2, 0],
						"34.0": [0.1, -1, 0],
						"34.2083": [0.1, -1.7, 0],
						"36.25": [0.1, -1.7, 0],
						"36.375": [0, 0, 0]
					},
					"scale": {
						"1.7917": [1, 1, 1],
						"1.9583": [1, 2.1, 1.1],
						"11.7083": [1, 2.1, 1.1],
						"11.9167": [1, 2.1, 1.1],
						"13.7083": [1, 2.1, 1.1],
						"32.0": [1, 2.1, 1.1],
						"32.2083": [1, 2.1, 1.1],
						"34.0": [1, 2.1, 1.1],
						"36.25": [1, 2.1, 1.1],
						"36.375": [1, 1, 1]
					}
				}
			}
		},
		"walk": {
			"loop": true,
			"animation_length": 0.33333,
			"bones": {
				"torso": {
					"rotation": {
						"0.0": [240.66403, 0.56803, -242.64578],
						"0.0417": [147.04868, 1.01415, -153.99292],
						"0.0833": [248.69858, 3.6701, -258.61099],
						"0.125": [242.75413, 2.72536, -247.67558],
						"0.1667": [260.07917, 5.48851, -252.96054],
						"0.2083": [255.767, 4.5619, -245.66478],
						"0.25": [250.28641, 3.64081, -244.19803],
						"0.2917": [198.16431, 1.38842, -198.61273],
						"0.3333": [226.82033, 1.96459, -230.25734]
					},
					"position": [0, 0, 0]
				},
				"mouth": {
					"rotation": {
						"0.0": [-0.07542, 0.34029, -9.99416],
						"0.0417": [-0.43751, -0.95371, -14.893],
						"0.0833": [-0.58765, -0.54818, -17.35335],
						"0.125": [-0.48468, 1.7573, -14.88537],
						"0.1667": [-0.48309, 7.38572, -9.96697],
						"0.2083": [-0.47566, 1.94296, -12.38513],
						"0.25": [-0.4587, 2.21442, -9.89935],
						"0.2917": [-0.28125, -2.82605, -2.37023],
						"0.3333": [-0.57583, 2.74222, -12.38695]
					}
				},
				"rightfront": {
					"rotation": {
						"0.0": [31.5, 0, 0],
						"0.0417": [42.5, 0, 0],
						"0.0833": [76.05449, -0.37577, 1.51932],
						"0.125": [46.06517, 0.43414, 1.50368],
						"0.1667": [1.06852, 1.37022, 0.75637],
						"0.2083": [-17.79445, 3.81506, 6.89514],
						"0.25": [7.01371, 0.55453, 7.85632],
						"0.2917": [26.8113, -2.33023, 6.59217],
						"0.3333": [31.78452, -2.89476, 6.36534]
					},
					"position": {
						"0.0": [0, 0, 0],
						"0.0417": [0, 0.1, 0],
						"0.0833": [0, 0.2, 0],
						"0.125": [0, 0.5, -0.1],
						"0.2083": [0, 1.03, -0.03],
						"0.25": [0, 0.4, 0],
						"0.3333": [0, 0.3, 0]
					}
				},
				"leftfront": {
					"rotation": {
						"0.0": [-1.53699, 1.10172, -3.84552],
						"0.0417": [-26.33728, -1.71048, -10.86782],
						"0.0833": [-26.15092, -2.67074, -11.08286],
						"0.125": [10.24292, 4.08121, -7.50796],
						"0.1667": [1.16499, 4.31487, -3.27719],
						"0.2083": [40.29554, 5.30908, 1.16981],
						"0.25": [60.35824, 4.58831, 2.91829],
						"0.2917": [70.8701, 3.97998, 3.70577],
						"0.3333": [16.69237, 5.33391, -1.05046]
					},
					"position": {
						"0.0": [0, 0.4, 0],
						"0.0417": [-0.1, 1.3, 0],
						"0.0833": [-0.1, 2.1, -0.1],
						"0.125": [-0.1, 1.5, 0.2],
						"0.1667": [0.4, 0.6, 0.1],
						"0.2083": [0.4, 0.5, 0.3],
						"0.25": [0.4, 0.8, 0.1],
						"0.2917": [0.4, 0.5, 0.6]
					}
				},
				"leftback": {
					"rotation": {
						"0.0": [29, 0, 0],
						"0.0417": [67.43432, 3.27573, -2.29681],
						"0.0833": [72.48761, 2.77061, -5.9391],
						"0.1667": [2.66527, -2.65858, -4.29089],
						"0.2083": [-31.3511, -4.60284, -20.07116],
						"0.25": [-9.2663, -4.77055, -24.9737],
						"0.2917": [3.95348, -20.58444, -5.82632],
						"0.3333": [28.43196, -8.78194, -23.2295]
					},
					"position": {
						"0.0": [0, 1, -0.9],
						"0.0417": [0, 1.3, -0.8],
						"0.0833": [0, 1.4, -0.6],
						"0.125": [0, 0.6, -0.4],
						"0.1667": [0.1, 0.2, -0.4],
						"0.2083": [0.1, 0.2, -0.4],
						"0.25": [0.1, 0.1, -0.4],
						"0.2917": [0.1, -0.3, -2.4],
						"0.3333": [0.1, 0.4, -1.9]
					}
				},
				"rightback": {
					"rotation": {
						"0.0": [-5, 0, 11],
						"0.0417": [-25.70229, 14.31181, 11.23538],
						"0.0833": [-8.30552, 6.22301, 7.49957],
						"0.125": [-2.33035, 5.40771, 8.10555],
						"0.1667": [34.87783, -2.51008, 12.08315],
						"0.2083": [60.497, -7.52966, 9.80144],
						"0.25": [20.7448, -1.46425, 5.00636],
						"0.2917": [16.3075, 1.52866, 12.2437],
						"0.3333": [-3.31632, 5.59952, 11.01099]
					},
					"position": {
						"0.0": [0, 0.5, -0.5],
						"0.0417": [-0.3, -0.5, -0.5],
						"0.0833": [-0.3, -0.9, -0.3],
						"0.125": [-0.3, 0.1, -0.3],
						"0.1667": [-0.1, 0.1, -0.3],
						"0.2083": [-0.1, 0.5, -0.3],
						"0.25": [-0.1, 0.6, -0.3]
					}
				},
				"2fr": {
					"rotation": {
						"0.0": [-16, 0, 0],
						"0.0417": [-26, 0, 0],
						"0.0833": [-39.99525, 0.13568, -0.35648],
						"0.125": [-6.00856, -0.33333, 0.42926],
						"0.1667": [3.98646, -0.55067, 0.5941],
						"0.2083": [-51.7138, 5.92362, -3.84429],
						"0.25": [-59.74375, 6.39192, -4.91703],
						"0.2917": [-16.71876, 3.06117, -0.48476],
						"0.3333": [-20.70062, 3.50036, -0.77569]
					}
				},
				"3fr": {
					"rotation": {
						"0.0": [-12.5, 0, 0],
						"0.0417": [-17.5, 0, 0],
						"0.0833": [25.48261, -1.10967, 0.2906],
						"0.125": [59.48051, -1.94682, -0.07903],
						"0.1667": [94.49894, -2.44105, -0.88057],
						"0.2083": [49.83016, 3.01336, -2.38429],
						"0.25": [53.81155, 2.59485, -2.0825],
						"0.2917": [-8.19237, -0.10472, -7.98528],
						"0.3333": [-15.1878, -0.19947, -8.20192]
					}
				},
				"2fl": {
					"rotation": {
						"0.0": [20, 0, 0],
						"0.0417": [-2.0791, -4.23959, -0.48029],
						"0.0833": [-58.86905, -4.25225, 7.20266],
						"0.125": [-80.47603, -7.90952, 7.56654],
						"0.1667": [-50.26383, -8.5527, 5.25376],
						"0.2083": [-36.13891, -8.83492, 4.11258],
						"0.25": [-59.28816, -7.90303, 5.57496],
						"0.2917": [-53.2572, -8.20144, 5.23242],
						"0.3333": [-0.8258, -8.9958, 1.49007]
					}
				},
				"3fl": {
					"rotation": {
						"0.0": [15, 0, 0],
						"0.0417": [29.73347, 2.84398, 0.2422],
						"0.0833": [24.81851, 1.90407, 0.08012],
						"0.125": [20.83356, 1.53798, -0.01711],
						"0.1667": [30.78083, 3.60443, 1.31409],
						"0.2083": [-1.19993, 3.79617, 1.58624],
						"0.25": [0.79907, 3.77999, 1.57274],
						"0.2917": [4.79697, 3.7491, 1.54409],
						"0.3333": [45.77034, 3.57241, 1.15965]
					}
				},
				"2lb": {
					"rotation": {
						"0.0": [-47.5, 0, 0],
						"0.0417": [-73.96564, -3.12732, 3.65906],
						"0.0833": [-54.92605, -2.85966, 2.71824],
						"0.125": [2.34556, 1.37406, -0.52911],
						"0.1667": [18.76844, 2.82387, -1.75837],
						"0.2083": [-35.62061, -12.3129, -2.01258],
						"0.25": [-55.34862, -25.76469, 22.944],
						"0.2917": [-77.15037, -20.57658, 15.46237],
						"0.3333": [-77.44063, 0.96719, 14.2786]
					}
				},
				"3lb": {
					"rotation": {
						"0.0": [12.5, 0, 0],
						"0.0417": [28.42299, 2.45911, 0.23515],
						"0.0833": [66.44199, 4.38021, 1.99427],
						"0.1667": [109.57242, 6.17605, 4.63251],
						"0.2083": [55.44547, 3.64956, 1.59516],
						"0.25": [47.1689, 0.44054, -0.22085],
						"0.2917": [73.31113, 21.96822, 23.69789],
						"0.3333": [55.22037, 3.48828, 22.65163]
					}
				},
				"2rb": {
					"rotation": {
						"0.0": [-32.5, 0, 0],
						"0.0417": [-44.07269, 2.99192, 0.81382],
						"0.0833": [-67.86507, 6.01178, -3.21224],
						"0.125": [-34.24958, 1.2944, 2.05923],
						"0.1667": [-33.28037, 1.06232, 2.16374],
						"0.2083": [-69.11869, 4.88879, 1.46155],
						"0.25": [-60.37935, 2.79227, 2.81081],
						"0.2917": [-16.08249, -9.56701, 4.15102],
						"0.3333": [-0.33493, -13.6107, 2.32821]
					}
				},
				"3rb": {
					"rotation": {
						"0.0": [7.5, 0, 0],
						"0.0417": [35.23241, -2.81469, -6.7442],
						"0.0833": [78.36473, 1.28911, -11.88393],
						"0.125": [36.35608, 1.29384, -12.40461],
						"0.1667": [-3.60295, 2.93401, -12.18434],
						"0.2083": [9.35969, 2.44918, -12.45753],
						"0.25": [13.17647, -13.86951, -119.51408],
						"0.2917": [19.25852, 2.31954, -13.51839],
						"0.3333": [35.09667, 2.49472, -15.21608]
					}
				}
			}
		},
		"attack": {
			"animation_length": 0.20833,
			"bones": {
				"torso": {
					"rotation": {
						"0.0": {
							"vector": [0, 0, 5]
						},
						"0.0417": {
							"vector": [0, 0, 5]
						},
						"0.125": {
							"vector": [-50.20385, 2.8236, 49.63879]
						},
						"0.1667": {
							"vector": [0, 0, 0]
						}
					},
					"position": {
						"0.0": {
							"vector": [0, 0, 0.4]
						},
						"0.0417": {
							"vector": [0, 0, 1.5]
						},
						"0.125": {
							"vector": [0, 0, -7.4]
						},
						"0.1667": {
							"vector": [0, 0, -0.4]
						}
					}
				},
				"mouth": {
					"rotation": {
						"0.0": {
							"vector": [0, 0, -12.5]
						},
						"0.0417": {
							"vector": [1.40682, -1.34832, -57.43311]
						},
						"0.125": {
							"vector": [-0.57848, 0.02589, 27.49036]
						},
						"0.1667": {
							"vector": [0, 0, 5]
						}
					}
				},
				"rightfront": {
					"rotation": {
						"0.0": {
							"vector": [0, 0, 0]
						},
						"0.125": {
							"vector": [7.5, 0, 0]
						},
						"0.1667": {
							"vector": [0, 0, 0]
						}
					},
					"position": {
						"0.0": {
							"vector": [0, 0, 0]
						},
						"0.125": {
							"vector": [0, 0, -5]
						},
						"0.1667": {
							"vector": [0, 0, 0]
						}
					}
				},
				"leftfront": {
					"rotation": {
						"vector": [7.5, 0, 0]
					},
					"position": {
						"0.0": {
							"vector": [0, 0, 0]
						},
						"0.125": {
							"vector": [0, 0, -6]
						},
						"0.1667": {
							"vector": [0, 0, 0]
						}
					},
					"scale": {
						"0.0": {
							"vector": [1, 1, 1]
						},
						"0.1667": {
							"vector": [1, 1, 1]
						}
					}
				},
				"leftback": {
					"rotation": {
						"0.0": {
							"vector": [0, 0, 0]
						},
						"0.125": {
							"vector": [7.5, 0, 0]
						},
						"0.1667": {
							"vector": [0, 0, 0]
						}
					},
					"position": {
						"0.0": {
							"vector": [0, 0, 0]
						},
						"0.125": {
							"vector": [0, 0, -6]
						},
						"0.1667": {
							"vector": [0, 0, 0]
						}
					}
				},
				"rightback": {
					"rotation": {
						"0.0": {
							"vector": [0, 0, 0]
						},
						"0.125": {
							"vector": [7.5, 0, 0]
						},
						"0.1667": {
							"vector": [0, 0, 0]
						}
					},
					"position": {
						"0.0": {
							"vector": [0, 0, 0]
						},
						"0.125": {
							"vector": [0, 0, -5]
						},
						"0.1667": {
							"vector": [0, 0, 0]
						}
					}
				}
			}
		}
	},
	"geckolib_format_version": 2
}